fmfug.py
fmfug-1.2.2.dist-info/LICENSE
fmfug-1.2.2.dist-info/METADATA
fmfug-1.2.2.dist-info/WHEEL
fmfug-1.2.2.dist-info/entry_points.txt
fmfug-1.2.2.dist-info/top_level.txt
fmfug-1.2.2.dist-info/RECORD
