Metadata-Version: 2.1
Name: fmfug
Version: 1.2.2
Summary: Fast Memory Friendly Username Generator
Author: Udodelige
License: MIT License
Project-URL: Homepage, https://github.com/0xudodelige/fmfug
Requires-Python: >=3.8
License-File: LICENSE
Requires-Dist: tqdm >=4.65.0
